yta_video_advanced_transitions/__init__.py
yta_video_advanced_transitions/objects.py
yta_video_advanced_transitions-0.0.2.dist-info/LICENSE
yta_video_advanced_transitions-0.0.2.dist-info/METADATA
yta_video_advanced_transitions-0.0.2.dist-info/WHEEL
yta_video_advanced_transitions-0.0.2.dist-info/RECORD
